cli/__init__.py
cli/__main__.py
cli/setup.py
cli/app/__init__.py
cli/app/__main__.py
cli/app/subcommand1.py
cli/app/subcommand2.py
cli/app/serve/__init__.py
cli/build/__init__.py
cli/build/__main__.py
cli/db/__init__.py
tree_commands/__init__.py
tree_commands/command.py
tree_commands/leaf.py
tree_commands/root.py
tree_commands-1.0.9.dist-info/LICENSE
tree_commands-1.0.9.dist-info/METADATA
tree_commands-1.0.9.dist-info/WHEEL
tree_commands-1.0.9.dist-info/entry_points.txt
tree_commands-1.0.9.dist-info/top_level.txt
tree_commands-1.0.9.dist-info/RECORD
