Metadata-Version: 2.1
Name: tree-commands
Version: 1.0.9
Summary: Build click commands using a tree directory structure
Home-page: https://github.com/gadc1996
Author: Gabriel Delgado
Author-email: gadc1996@gmail.com
Classifier: Development Status :: 3 - Alpha
Classifier: Intended Audience :: Developers
Classifier: License :: OSI Approved :: MIT License
Classifier: Programming Language :: Python :: 3
Classifier: Programming Language :: Python :: 3.6
Classifier: Programming Language :: Python :: 3.7
Classifier: Programming Language :: Python :: 3.8
Classifier: Programming Language :: Python :: 3.9
License-File: LICENSE
Requires-Dist: click
